fodantic/__init__.py
fodantic/form.py
fodantic/form_field.py
fodantic/parser.py
fodantic/wrappers.py
fodantic-0.1.dist-info/METADATA
fodantic-0.1.dist-info/WHEEL
fodantic-0.1.dist-info/top_level.txt
fodantic-0.1.dist-info/RECORD
