Metadata-Version: 2.4
Name: fodantic
Version: 0.1
Summary: Pydantic-based HTTP forms
Author-email: Juan-Pablo Scaletti <juanpablo@jpscaletti.com>
License: Copyright (c) Juan-Pablo Scaletti
Project-URL: repository, https://github.com/jpsca/fodantic
Classifier: Development Status :: 4 - Beta
Classifier: Environment :: Web Environment
Classifier: Intended Audience :: Developers
Classifier: License :: OSI Approved :: MIT License
Classifier: Programming Language :: Python :: 3 :: Only
Classifier: Programming Language :: Python :: 3.10
Classifier: Programming Language :: Python :: 3.11
Classifier: Programming Language :: Python :: 3.12
Classifier: Programming Language :: Python :: 3.13
Classifier: Typing :: Typed
Requires-Python: <4,>=3.10
Requires-Dist: pydantic>=2.6.0
